py_commons_ip/__init__.py
py_commons_ip/resources/commons-ip2-cli.jar
py_commons_ip-0.3.2.dist-info/licenses/LICENSE
py_commons_ip-0.3.2.dist-info/METADATA
py_commons_ip-0.3.2.dist-info/WHEEL
py_commons_ip-0.3.2.dist-info/top_level.txt
py_commons_ip-0.3.2.dist-info/RECORD
