Metadata-Version: 2.4
Name: py-commons-ip
Version: 0.3.2
Summary: A wrapper library to use the commons-ip library in Python
Classifier: Programming Language :: Python :: 3.10
Requires-Python: >=3.10
License-File: LICENSE
Provides-Extra: dev
Requires-Dist: pytest==8.4.1; extra == "dev"
Requires-Dist: ruff==0.12.7; extra == "dev"
Requires-Dist: build==1.3.0; extra == "dev"
Requires-Dist: twine==6.1.0; extra == "dev"
Dynamic: license-file
